flagright/__init__.py
flagright/batch/__init__.py
flagright/batch/client.py
flagright/batch/raw_client.py
flagright/business_user_events/__init__.py
flagright/business_user_events/client.py
flagright/business_user_events/raw_client.py
flagright/business_users/__init__.py
flagright/business_users/client.py
flagright/business_users/raw_client.py
flagright/business_users/types/__init__.py
flagright/business_users/types/business_users_create_response.py
flagright/client.py
flagright/consumer_user_events/__init__.py
flagright/consumer_user_events/client.py
flagright/consumer_user_events/raw_client.py
flagright/consumer_users/__init__.py
flagright/consumer_users/client.py
flagright/consumer_users/raw_client.py
flagright/consumer_users/types/__init__.py
flagright/consumer_users/types/consumer_users_create_response.py
flagright/core/__init__.py
flagright/core/api_error.py
flagright/core/client_wrapper.py
flagright/core/datetime_utils.py
flagright/core/file.py
flagright/core/force_multipart.py
flagright/core/http_client.py
flagright/core/http_response.py
flagright/core/jsonable_encoder.py
flagright/core/pydantic_utilities.py
flagright/core/query_encoder.py
flagright/core/remove_none_from_dict.py
flagright/core/request_options.py
flagright/core/serialization.py
flagright/environment.py
flagright/errors/__init__.py
flagright/errors/bad_request_error.py
flagright/errors/conflict_error.py
flagright/errors/not_found_error.py
flagright/errors/too_many_requests_error.py
flagright/errors/unauthorized_error.py
flagright/py.typed
flagright/transaction_events/__init__.py
flagright/transaction_events/client.py
flagright/transaction_events/raw_client.py
flagright/transactions/__init__.py
flagright/transactions/client.py
flagright/transactions/raw_client.py
flagright/transactions/types/__init__.py
flagright/transactions/types/transactions_verify_response.py
flagright/types/__init__.py
flagright/types/ach_details.py
flagright/types/ach_payment_method.py
flagright-1.8.38.dist-info/METADATA
flagright-1.8.38.dist-info/WHEEL
flagright-1.8.38.dist-info/RECORD
